Metadata-Version: 2.1
Name: livecover
Version: 0.0.14
Summary: The livecover python package
Home-page: https://github.com/rafalstapinski/livecover-py
Author: Rafal Stapinski
Author-email: stapinskirafal@gmail.com
License: BSD
Download-URL: https://github.com/rafalstapinski/livecover-py/archive/0.0.14.tar.gz
Keywords: live code coverage
Platform: UNKNOWN
Classifier: Development Status :: 3 - Alpha
Classifier: Intended Audience :: Developers
Classifier: Topic :: Software Development :: Quality Assurance
Classifier: License :: OSI Approved :: BSD License
Classifier: Programming Language :: Python :: 3.8
